EasyProxies/__init__.py
EasyProxies/_proxy_descriptor.py
EasyProxies/const.py
EasyProxies-2.0.1.dist-info/LICENSE
EasyProxies-2.0.1.dist-info/METADATA
EasyProxies-2.0.1.dist-info/WHEEL
EasyProxies-2.0.1.dist-info/top_level.txt
EasyProxies-2.0.1.dist-info/RECORD
