Metadata-Version: 2.1
Name: EasyProxies
Version: 2.0.1
Summary: A simple and quick way to get a proxy.
Home-page: https://github.com/NIKDISSV-Forever/proxyscan
Author: Nikita (NIKDISSV)
Author-email: nikdissv@proton.me
Classifier: Programming Language :: Python :: 3
Classifier: Development Status :: 5 - Production/Stable
Classifier: License :: OSI Approved :: MIT License
Classifier: Operating System :: OS Independent
Classifier: Typing :: Typed
Requires-Python: >=3.9
License-File: LICENSE
